arc/__init__.py
arc/app.py
arc/collections.py
arc/defaults.py
arc/errors.py
arc/forms.py
arc/logger.py
arc/middleware.py
arc/responses.py
arc/sessions.py
arc/setup.py
arc/staticfiles.py
arc/templates.py
arc/selfpages/error-404.html
arc/selfpages/error-500.html
arc/selfpages/index.html
arc/static/error404.css
arcframework-2.7.1.dist-info/LICENSE.txt
arcframework-2.7.1.dist-info/METADATA
arcframework-2.7.1.dist-info/WHEEL
arcframework-2.7.1.dist-info/top_level.txt
arcframework-2.7.1.dist-info/RECORD
