Metadata-Version: 2.1
Name: arcframework
Version: 2.7.1
Summary: A Python micro web framework for creating dynamic websites.
Home-page: https://github.com/AbooMinister25/arc
Author: Rayyan Cyclegar
Author-email: aboominister@gmail.com
License: UNKNOWN
Platform: UNKNOWN
Classifier: Programming Language :: Python :: 3
Classifier: License :: OSI Approved :: MIT License
Classifier: Operating System :: OS Independent
Requires-Python: >=3.8
Requires-Dist: uvicorn
Requires-Dist: parse
Requires-Dist: jinja2
Requires-Dist: starlette
Requires-Dist: orjson
